deepdraken/__init__.py
deepdraken/_version.py
deepdraken/base.py
deepdraken/experimental/__init__.py
deepdraken/experimental/image_generation/__init__.py
deepdraken/experimental/image_generation/big_gan.py
deepdraken/experimental/image_generation/compare_gan.py
deepdraken/image_generation/__init__.py
deepdraken/image_generation/gans/__init__.py
deepdraken/image_generation/gans/cgan.py
deepdraken/image_generation/gans/dcgan.py
deepdraken/image_generation/gans/wgan.py
deepdraken/utils/__init__.py
deepdraken/utils/base_utils.py
deepdraken/utils/utils.py
deepdraken-0.0.1.dist-info/LICENSE
deepdraken-0.0.1.dist-info/METADATA
deepdraken-0.0.1.dist-info/WHEEL
deepdraken-0.0.1.dist-info/top_level.txt
deepdraken-0.0.1.dist-info/RECORD
