Metadata-Version: 2.1
Name: deepdraken
Version: 0.0.1
Summary: Package for CV tasks
Home-page: https://github.com/DevavratSinghBisht/deepdraken
Author: Devavrat Singh Bisht
Author-email: devavratsinghbisht@gmail.com
License: Apache License 2.0
Download-URL: https://github.com/DevavratSinghBisht/deepdraken
Keywords: Computer-Vision Transfer-Learning
Platform: UNKNOWN
Classifier: Intended Audience :: Science/Research
Classifier: License :: OSI Approved :: Apache Software License
Classifier: Programming Language :: Python :: 3
Classifier: Operating System :: OS Independent
Classifier: Topic :: Scientific/Engineering :: Artificial Intelligence
Requires-Python: >=3.6.0
License-File: LICENSE
Requires-Dist: tqdm
Requires-Dist: numpy
Requires-Dist: scipy
Requires-Dist: torch
Requires-Dist: torchvision
